agentpay/__init__.py
agentpay/core.py
agentpay_sdk_python-0.1.0.dist-info/METADATA
agentpay_sdk_python-0.1.0.dist-info/WHEEL
agentpay_sdk_python-0.1.0.dist-info/top_level.txt
agentpay_sdk_python-0.1.0.dist-info/RECORD
