Metadata-Version: 2.4
Name: agentpay-sdk-python
Version: 0.1.0
Summary: Infraestructura financiera universal para Agentes de IA
Author: Jairo Gelpi
Author-email: jairo.gelpi@agentpay.io
Classifier: Programming Language :: Python :: 3
Classifier: License :: OSI Approved :: MIT License
Classifier: Operating System :: OS Independent
Requires-Python: >=3.7
Requires-Dist: requests>=2.25.0
Dynamic: author
Dynamic: author-email
Dynamic: classifier
Dynamic: requires-dist
Dynamic: requires-python
Dynamic: summary
